randomcatimage/__init__.py
randomcatimage-1.0.2.dist-info/METADATA
randomcatimage-1.0.2.dist-info/WHEEL
randomcatimage-1.0.2.dist-info/top_level.txt
randomcatimage-1.0.2.dist-info/RECORD
